headfake/__init__.py
headfake/__init__.pyc
headfake/cli.py
headfake/cli.pyc
headfake/error.py
headfake/fieldset.py
headfake/headfake.py
headfake/output.py
headfake/output.pyc
headfake/transformer.py
headfake/util.py
headfake/examples/admission.json
headfake/examples/patients.yaml
headfake/examples/screening.yaml
headfake/examples/test_data/patients.txt
headfake/field/__init__.py
headfake/field/core.py
headfake/field/derived.py
headfake/field/faker.py
headfake/field/id.py
tests/__init__.py
tests/pytest.ini
tests/test_cli.py
tests/test_examples.py
tests/test_fieldset.py
tests/test_transformer.py
tests/test_util.py
tests/field/__init__.py
tests/field/test_field_common.py
tests/field/test_field_core.py
tests/field/test_field_derived.py
tests/field/test_field_faker.py
tests/field/test_field_id.py
tests/templates/example_data.txt
tests/templates/test1.yaml
tests/templates/test2.yaml
tests/templates/test3.yaml
headfake-1.1.1.dist-info/LICENSE.md
headfake-1.1.1.dist-info/METADATA
headfake-1.1.1.dist-info/WHEEL
headfake-1.1.1.dist-info/entry_points.txt
headfake-1.1.1.dist-info/top_level.txt
headfake-1.1.1.dist-info/RECORD
