Metadata-Version: 2.1
Name: headfake
Version: 1.1.1
Summary: Health data faker
Home-page: https://github.com/rcfgroup/headfake
Author: Rob Free
Author-email: rcfree@pm.me
License: MIT
Keywords: fake,data,generation,faker,pydbgen
Requires-Python: >=3.6
License-File: LICENSE.md
Requires-Dist: attrs
Requires-Dist: faker
Requires-Dist: pandas
Requires-Dist: pyyaml
Requires-Dist: scipy
Provides-Extra: all
Provides-Extra: dev
Requires-Dist: pytest ; extra == 'dev'
Requires-Dist: pytest-cov ; extra == 'dev'
Requires-Dist: pytest-mock ; extra == 'dev'
Requires-Dist: mkdocs ; extra == 'dev'
Requires-Dist: mkapi ; extra == 'dev'
Requires-Dist: twine ; extra == 'dev'
Requires-Dist: wheel ; extra == 'dev'
Provides-Extra: docs
Requires-Dist: mkdocs ; extra == 'docs'
Requires-Dist: mkapi ; extra == 'docs'
Provides-Extra: tests
Requires-Dist: pytest ; extra == 'tests'
Requires-Dist: pytest-cov ; extra == 'tests'
Requires-Dist: pytest-mock ; extra == 'tests'
